MANIFEST.in
README.md
setup.py
spark_df_profiling/__init__.py
spark_df_profiling/base.py
spark_df_profiling/formatters.py
spark_df_profiling/lookup_object.py
spark_df_profiling/spark_df_profiling.mplstyle
spark_df_profiling/templates.py
spark_df_profiling/tests.py.old.py
spark_df_profiling/templates/_row_footer.html
spark_df_profiling/templates/_row_header.html
spark_df_profiling/templates/_row_header_ignore.html
spark_df_profiling/templates/base.html
spark_df_profiling/templates/freq_table.html
spark_df_profiling/templates/freq_table_row.html
spark_df_profiling/templates/mini_freq_table.html
spark_df_profiling/templates/mini_freq_table_row.html
spark_df_profiling/templates/overview.html
spark_df_profiling/templates/row_cat.html
spark_df_profiling/templates/row_const.html
spark_df_profiling/templates/row_corr.html
spark_df_profiling/templates/row_date.html
spark_df_profiling/templates/row_num.html
spark_df_profiling/templates/row_unique.html
spark_df_profiling/templates/sample.html
spark_df_profiling/templates/wrapper.html
spark_df_profiling/templates/wrapper_static.html
spark_df_profiling/templates/css/bootstrap-theme.min.css
spark_df_profiling/templates/css/bootstrap.min.css
spark_df_profiling/templates/js/bootstrap.min.js
spark_df_profiling/templates/js/jquery.min.js
spark_df_profiling_new.egg-info/PKG-INFO
spark_df_profiling_new.egg-info/SOURCES.txt
spark_df_profiling_new.egg-info/dependency_links.txt
spark_df_profiling_new.egg-info/requires.txt
spark_df_profiling_new.egg-info/top_level.txt